hypermodern_screening/__init__.py
hypermodern_screening/sampling_schemes.py
hypermodern_screening/screening_measures.py
hypermodern_screening/select_sample_set.py
hypermodern_screening/transform_distributions.py
hypermodern_screening/transform_ee.py
hypermodern_screening/transform_reorder.py
hypermodern_screening-0.0.4.dist-info/LICENSE
hypermodern_screening-0.0.4.dist-info/WHEEL
hypermodern_screening-0.0.4.dist-info/METADATA
hypermodern_screening-0.0.4.dist-info/RECORD
