Metadata-Version: 2.1
Name: hypermodern-screening
Version: 0.0.4
Summary: The hypermodern screening project
Home-page: https://github.com/tostenzel/hypermodern-screening
License: MIT
Keywords: hypermodern,screening,uncertainty-quantification,global-sensitivity-analysis,screening,sampling-methods
Author: tostenzel
Author-email: tobias.stenzel@mailbox.org
Requires-Python: >=3.7,<4.0
Classifier: License :: OSI Approved :: MIT License
Classifier: Programming Language :: Python :: 3
Classifier: Programming Language :: Python :: 3.7
Classifier: Programming Language :: Python :: 3.8
Requires-Dist: chaospy (>=3.2.7,<4.0.0)
Project-URL: Documentation, https://hypermodern-screening.readthedocs.io
Project-URL: Repository, https://github.com/tostenzel/hypermodern-screening
